MANIFEST.in
README.md
requirements.txt
setup.py
docs_raw/__init__.py
docs_raw/source/__init__.py
docs_raw/source/conf.py
rl_coach/__init__.py
rl_coach/base_parameters.py
rl_coach/checkpoint.py
rl_coach/coach.py
rl_coach/core_types.py
rl_coach/dashboard.py
rl_coach/debug_utils.py
rl_coach/level_manager.py
rl_coach/logger.py
rl_coach/plot_atari.py
rl_coach/renderer.py
rl_coach/rollout_worker.py
rl_coach/run_multiple_seeds.py
rl_coach/saver.py
rl_coach/schedules.py
rl_coach/spaces.py
rl_coach/training_worker.py
rl_coach/utils.py
rl_coach/agents/__init__.py
rl_coach/agents/acer_agent.py
rl_coach/agents/actor_critic_agent.py
rl_coach/agents/agent.py
rl_coach/agents/agent_interface.py
rl_coach/agents/bc_agent.py
rl_coach/agents/bootstrapped_dqn_agent.py
rl_coach/agents/categorical_dqn_agent.py
rl_coach/agents/cil_agent.py
rl_coach/agents/clipped_ppo_agent.py
rl_coach/agents/composite_agent.py
rl_coach/agents/ddpg_agent.py
rl_coach/agents/ddqn_agent.py
rl_coach/agents/ddqn_bcq_agent.py
rl_coach/agents/dfp_agent.py
rl_coach/agents/dqn_agent.py
rl_coach/agents/hac_ddpg_agent.py
rl_coach/agents/human_agent.py
rl_coach/agents/imitation_agent.py
rl_coach/agents/mmc_agent.py
rl_coach/agents/n_step_q_agent.py
rl_coach/agents/naf_agent.py
rl_coach/agents/nec_agent.py
rl_coach/agents/pal_agent.py
rl_coach/agents/policy_gradients_agent.py
rl_coach/agents/policy_optimization_agent.py
rl_coach/agents/ppo_agent.py
rl_coach/agents/qr_dqn_agent.py
rl_coach/agents/rainbow_dqn_agent.py
rl_coach/agents/soft_actor_critic_agent.py
rl_coach/agents/td3_agent.py
rl_coach/agents/value_optimization_agent.py
rl_coach/agents/wolpertinger_agent.py
rl_coach/architectures/__init__.py
rl_coach/architectures/architecture.py
rl_coach/architectures/embedder_parameters.py
rl_coach/architectures/head_parameters.py
rl_coach/architectures/layers.py
rl_coach/architectures/middleware_parameters.py
rl_coach/architectures/network_wrapper.py
rl_coach/architectures/mxnet_components/__init__.py
rl_coach_slim.egg-info/PKG-INFO
rl_coach_slim.egg-info/SOURCES.txt
rl_coach_slim.egg-info/dependency_links.txt
rl_coach_slim.egg-info/entry_points.txt
rl_coach_slim.egg-info/requires.txt
rl_coach_slim.egg-info/top_level.txt